pytest_exit_status/__init__.py
pytest_exit_status/plugin.py
pytest_exit_status-1.0.0.dist-info/entry_points.txt
pytest_exit_status-1.0.0.dist-info/WHEEL
pytest_exit_status-1.0.0.dist-info/METADATA
pytest_exit_status-1.0.0.dist-info/RECORD
