Metadata-Version: 2.3
Name: pytest-exit-status
Version: 1.0.0
Summary: Enhance.
Keywords: pytest,pytest-html
Author-email: Harmin Parra Rueda <harmin.rueda@gmail.com>
Requires-Python: >=3.10
Classifier: Framework :: Pytest
Classifier: License :: OSI Approved :: MIT License
Classifier: Topic :: Software Development :: Quality Assurance
Classifier: Topic :: Software Development :: Testing
Requires-Dist: pytest >= 8.0.0
